{
  "timestamp" : "2024-11-24T12:28:37Z",
  "count_outdated" : 1475,
  "uniques_outdated" : 404,
  "count" : 1499,
  "uniques" : 415,
  "views" : [
    {
      "timestamp": "2024-11-10T00:00:00Z",
      "count": 1,
      "count_minmax": [ 1, 1 ],
      "count_decinc": [ 0, 1 ],
      "uniques": 1,
      "uniques_minmax": [ 1, 1 ],
      "uniques_decinc": [ 0, 1 ]
    },
    {
      "timestamp": "2024-11-11T00:00:00Z",
      "count": 1,
      "count_minmax": [ 1, 1 ],
      "count_decinc": [ 0, 1 ],
      "uniques": 1,
      "uniques_minmax": [ 1, 1 ],
      "uniques_decinc": [ 0, 1 ]
    },
    {
      "timestamp": "2024-11-12T00:00:00Z",
      "count": 8,
      "count_minmax": [ 8, 8 ],
      "count_decinc": [ 0, 8 ],
      "uniques": 2,
      "uniques_minmax": [ 2, 2 ],
      "uniques_decinc": [ 0, 2 ]
    },
    {
      "timestamp": "2024-11-13T00:00:00Z",
      "count": 2,
      "count_minmax": [ 2, 2 ],
      "count_decinc": [ 0, 2 ],
      "uniques": 1,
      "uniques_minmax": [ 1, 1 ],
      "uniques_decinc": [ 0, 1 ]
    },
    {
      "timestamp": "2024-11-14T00:00:00Z",
      "count": 2,
      "count_minmax": [ 2, 2 ],
      "count_decinc": [ 0, 2 ],
      "uniques": 1,
      "uniques_minmax": [ 1, 1 ],
      "uniques_decinc": [ 0, 1 ]
    },
    {
      "timestamp": "2024-11-19T00:00:00Z",
      "count": 1,
      "count_minmax": [ 1, 1 ],
      "count_decinc": [ 0, 1 ],
      "uniques": 1,
      "uniques_minmax": [ 1, 1 ],
      "uniques_decinc": [ 0, 1 ]
    },
    {
      "timestamp": "2024-11-20T00:00:00Z",
      "count": 2,
      "count_minmax": [ 2, 2 ],
      "count_decinc": [ 0, 2 ],
      "uniques": 1,
      "uniques_minmax": [ 1, 1 ],
      "uniques_decinc": [ 0, 1 ]
    },
    {
      "timestamp": "2024-11-21T00:00:00Z",
      "count": 1,
      "count_minmax": [ 1, 1 ],
      "count_decinc": [ 0, 1 ],
      "uniques": 1,
      "uniques_minmax": [ 1, 1 ],
      "uniques_decinc": [ 0, 1 ]
    },
    {
      "timestamp": "2024-11-23T00:00:00Z",
      "count": 1,
      "count_minmax": [ 1, 1 ],
      "count_decinc": [ 0, 1 ],
      "uniques": 1,
      "uniques_minmax": [ 1, 1 ],
      "uniques_decinc": [ 0, 1 ]
    },
    {
      "timestamp": "2024-11-24T00:00:00Z",
      "count": 5,
      "count_minmax": [ 5, 5 ],
      "count_decinc": [ 0, 5 ],
      "uniques": 1,
      "uniques_minmax": [ 1, 1 ],
      "uniques_decinc": [ 0, 1 ]
    }
  ]
}
